{
    "version": "1.5.2",
    "description": "将 Dalvik 字节码从 APK、dex、aar、aab 和 zip 文件反编译为 Java 代码 decode 和其他资源AndroidManifest.xmlresources.arsc 包括 deobfuscator",
    "notes":[
        "安卓逆向",
        "反编译工具"
    ],
    "homepage": "https://github.com/skylot/jadx",
    "license": "Apache-2.0",
    "url": "https://github.com/skylot/jadx/releases/download/v1.5.2/jadx-gui-1.5.2-with-jre-win.zip",
    "hash": "c5960adf0decc10bbc0c788fae6147e1d66793c781e76d0c6d00e050410984f2",
    "pre_install": "Get-ChildItem \"$dir\" 'jadx-gui-*.exe' | Select-Object -First 1 | Rename-Item -NewName 'jadx-gui.exe'",
    "bin": "jadx-gui.exe",
    "shortcuts": [
        [
            "jadx-gui.exe",
            "jadx"
        ]
    ],
    "checkver": "github",
    "autoupdate": {
        "url": "https://github.com/skylot/jadx/releases/download/v$version/jadx-gui-$version-with-jre-win.zip"
    }
}
